HA23039UNO/__init__.py
HA23039UNO/linear_methods.py
HA23039UNO/nonlinear_methods.py
HA23039UNO/utils.py
HA23039UNO-0.1.0.dist-info/LICENCE
HA23039UNO-0.1.0.dist-info/METADATA
HA23039UNO-0.1.0.dist-info/WHEEL
HA23039UNO-0.1.0.dist-info/top_level.txt
HA23039UNO-0.1.0.dist-info/RECORD
