Metadata-Version: 2.1
Name: HA23039UNO
Version: 0.1.0
Summary: Librería para resolver sistemas de ecuaciones lineales y no lineales
Home-page: https://github.com/tuusuario/HA23039UNO
Author: Tu Nombre
Author-email: tu.email@ejemplo.com
Classifier: Programming Language :: Python :: 3
Classifier: License :: OSI Approved :: MIT License
Classifier: Operating System :: OS Independent
Requires-Python: >=3.6
License-File: LICENCE
